{
  "last_updated": "2026-06-25T04:27:54.763Z",
  "results": {
    "11:00 AM": {
      "set": "1565.26",
      "value": "32206.68",
      "twod": "66",
      "date": "2026-06-25",
      "is_locked": false,
      "updated_at": "2026-06-25T04:27:54.763Z"
    },
    "12:01 PM": {
      "set": "--",
      "value": "--",
      "twod": "--",
      "date": "2026-06-25",
      "is_locked": false
    },
    "3:00 PM": {
      "set": "--",
      "value": "--",
      "twod": "--",
      "date": "2026-06-25",
      "is_locked": false
    },
    "4:30 PM": {
      "set": "--",
      "value": "--",
      "twod": "--",
      "date": "2026-06-25",
      "is_locked": false
    }
  },
  "latest_result": {
    "set": "1565.26",
    "value": "32206.68",
    "twod": "66",
    "updated_at": "2026-06-25T04:27:54.763Z"
  }
}