{
  "last_updated": "2026-07-20T03:55:54.176Z",
  "results": {
    "11:00 AM": {
      "set": "1637.00",
      "value": "30425.48",
      "twod": "05",
      "date": "2026-07-20",
      "is_locked": false,
      "updated_at": "2026-07-20T03:55:54.176Z"
    },
    "12:01 PM": {
      "set": "--",
      "value": "--",
      "twod": "--",
      "date": "2026-07-20",
      "is_locked": false
    },
    "3:00 PM": {
      "set": "--",
      "value": "--",
      "twod": "--",
      "date": "2026-07-20",
      "is_locked": false
    },
    "4:30 PM": {
      "set": "--",
      "value": "--",
      "twod": "--",
      "date": "2026-07-20",
      "is_locked": false
    }
  },
  "latest_result": {
    "set": "1637.00",
    "value": "30425.48",
    "twod": "05",
    "updated_at": "2026-07-20T03:55:54.176Z"
  }
}