{
  "last_updated": "2026-06-04T04:56:54.339Z",
  "results": {
    "11:00 AM": {
      "set": "--",
      "value": "--",
      "twod": "--",
      "date": "2026-06-04",
      "is_locked": false,
      "updated_at": "2026-06-04T04:56:54.339Z"
    },
    "12:01 PM": {
      "set": "1600.52",
      "value": "50219.78",
      "twod": "29",
      "date": "2026-06-04",
      "is_locked": false,
      "updated_at": "2026-06-04T04:56:54.339Z"
    },
    "3:00 PM": {
      "set": "--",
      "value": "--",
      "twod": "--",
      "date": "2026-06-04",
      "is_locked": false
    },
    "4:30 PM": {
      "set": "--",
      "value": "--",
      "twod": "--",
      "date": "2026-06-04",
      "is_locked": false
    }
  },
  "latest_result": {
    "set": "1600.52",
    "value": "50219.78",
    "twod": "29",
    "updated_at": "2026-06-04T04:56:54.339Z"
  }
}