{
  "last_updated": "2026-07-01T04:09:54.345Z",
  "results": {
    "11:00 AM": {
      "set": "1599.24",
      "value": "30147.42",
      "twod": "47",
      "date": "2026-07-01",
      "is_locked": false,
      "updated_at": "2026-07-01T04:09:54.345Z"
    },
    "12:01 PM": {
      "set": "--",
      "value": "--",
      "twod": "--",
      "date": "2026-07-01",
      "is_locked": false
    },
    "3:00 PM": {
      "set": "--",
      "value": "--",
      "twod": "--",
      "date": "2026-07-01",
      "is_locked": false
    },
    "4:30 PM": {
      "set": "--",
      "value": "--",
      "twod": "--",
      "date": "2026-07-01",
      "is_locked": false
    }
  },
  "latest_result": {
    "set": "1599.24",
    "value": "30147.42",
    "twod": "47",
    "updated_at": "2026-07-01T04:09:54.345Z"
  }
}