{
  "last_updated": "2026-07-07T03:55:54.596Z",
  "results": {
    "11:00 AM": {
      "set": "1597.75",
      "value": "35586.22",
      "twod": "56",
      "date": "2026-07-07",
      "is_locked": false,
      "updated_at": "2026-07-07T03:55:54.596Z"
    },
    "12:01 PM": {
      "set": "--",
      "value": "--",
      "twod": "--",
      "date": "2026-07-07",
      "is_locked": false
    },
    "3:00 PM": {
      "set": "--",
      "value": "--",
      "twod": "--",
      "date": "2026-07-07",
      "is_locked": false
    },
    "4:30 PM": {
      "set": "--",
      "value": "--",
      "twod": "--",
      "date": "2026-07-07",
      "is_locked": false
    }
  },
  "latest_result": {
    "set": "1597.75",
    "value": "35586.22",
    "twod": "56",
    "updated_at": "2026-07-07T03:55:54.596Z"
  }
}