{
  "last_updated": "2026-06-24T03:57:54.719Z",
  "results": {
    "11:00 AM": {
      "set": "1545.58",
      "value": "21810.05",
      "twod": "80",
      "date": "2026-06-24",
      "is_locked": false,
      "updated_at": "2026-06-24T03:57:54.719Z"
    },
    "12:01 PM": {
      "set": "--",
      "value": "--",
      "twod": "--",
      "date": "2026-06-24",
      "is_locked": false
    },
    "3:00 PM": {
      "set": "--",
      "value": "--",
      "twod": "--",
      "date": "2026-06-24",
      "is_locked": false
    },
    "4:30 PM": {
      "set": "--",
      "value": "--",
      "twod": "--",
      "date": "2026-06-24",
      "is_locked": false
    }
  },
  "latest_result": {
    "set": "1545.58",
    "value": "21810.05",
    "twod": "80",
    "updated_at": "2026-06-24T03:57:54.719Z"
  }
}