{
  "last_updated": "2026-06-22T03:38:54.736Z",
  "results": {
    "11:00 AM": {
      "set": "--",
      "value": "--",
      "twod": "--",
      "date": "2026-06-22",
      "is_locked": false
    },
    "12:01 PM": {
      "set": "--",
      "value": "--",
      "twod": "--",
      "date": "2026-06-22",
      "is_locked": false
    },
    "3:00 PM": {
      "set": "--",
      "value": "--",
      "twod": "--",
      "date": "2026-06-22",
      "is_locked": false
    },
    "4:30 PM": {
      "set": "--",
      "value": "--",
      "twod": "--",
      "date": "2026-06-22",
      "is_locked": false
    }
  },
  "latest_result": {
    "set": "1575.25",
    "value": "21719.26",
    "twod": "59",
    "updated_at": "2026-06-22T03:38:54.736Z"
  }
}