{
  "last_updated": "2026-07-07T04:30:54.347Z",
  "results": {
    "11:00 AM": {
      "set": "1602.33",
      "value": "43243.03",
      "twod": "33",
      "date": "2026-07-07",
      "is_locked": false,
      "updated_at": "2026-07-07T04:30:54.347Z"
    },
    "12:01 PM": {
      "set": "--",
      "value": "--",
      "twod": "--",
      "date": "2026-07-07",
      "is_locked": false
    },
    "3:00 PM": {
      "set": "--",
      "value": "--",
      "twod": "--",
      "date": "2026-07-07",
      "is_locked": false
    },
    "4:30 PM": {
      "set": "--",
      "value": "--",
      "twod": "--",
      "date": "2026-07-07",
      "is_locked": false
    }
  },
  "latest_result": {
    "set": "1602.33",
    "value": "43243.03",
    "twod": "33",
    "updated_at": "2026-07-07T04:30:54.347Z"
  }
}