{
  "last_updated": "2026-07-13T03:14:54.702Z",
  "results": {
    "11:00 AM": {
      "set": "--",
      "value": "--",
      "twod": "--",
      "date": "2026-07-13",
      "is_locked": false
    },
    "12:01 PM": {
      "set": "--",
      "value": "--",
      "twod": "--",
      "date": "2026-07-13",
      "is_locked": false
    },
    "3:00 PM": {
      "set": "--",
      "value": "--",
      "twod": "--",
      "date": "2026-07-13",
      "is_locked": false
    },
    "4:30 PM": {
      "set": "--",
      "value": "--",
      "twod": "--",
      "date": "2026-07-13",
      "is_locked": false
    }
  },
  "latest_result": {
    "set": "1614.09",
    "value": "14273.26",
    "twod": "93",
    "updated_at": "2026-07-13T03:14:54.702Z"
  }
}