{
  "last_updated": "2026-06-16T03:53:54.712Z",
  "results": {
    "11:00 AM": {
      "set": "1591.41",
      "value": "26247.06",
      "twod": "17",
      "date": "2026-06-16",
      "is_locked": false,
      "updated_at": "2026-06-16T03:53:54.712Z"
    },
    "12:01 PM": {
      "set": "--",
      "value": "--",
      "twod": "--",
      "date": "2026-06-16",
      "is_locked": false
    },
    "3:00 PM": {
      "set": "--",
      "value": "--",
      "twod": "--",
      "date": "2026-06-16",
      "is_locked": false
    },
    "4:30 PM": {
      "set": "--",
      "value": "--",
      "twod": "--",
      "date": "2026-06-16",
      "is_locked": false
    }
  },
  "latest_result": {
    "set": "1591.41",
    "value": "26247.06",
    "twod": "17",
    "updated_at": "2026-06-16T03:53:54.712Z"
  }
}