{
  "last_updated": "2026-07-13T03:50:54.210Z",
  "results": {
    "11:00 AM": {
      "set": "1621.39",
      "value": "25610.20",
      "twod": "90",
      "date": "2026-07-13",
      "is_locked": false,
      "updated_at": "2026-07-13T03:50:54.210Z"
    },
    "12:01 PM": {
      "set": "--",
      "value": "--",
      "twod": "--",
      "date": "2026-07-13",
      "is_locked": false
    },
    "3:00 PM": {
      "set": "--",
      "value": "--",
      "twod": "--",
      "date": "2026-07-13",
      "is_locked": false
    },
    "4:30 PM": {
      "set": "--",
      "value": "--",
      "twod": "--",
      "date": "2026-07-13",
      "is_locked": false
    }
  },
  "latest_result": {
    "set": "1621.39",
    "value": "25610.20",
    "twod": "90",
    "updated_at": "2026-07-13T03:50:54.210Z"
  }
}